{
    "asset": {
        "format": "jpeg",
        "id": "5e7fe1809a5d63f2f711066814c92df1",
        "name": "sea%20grass_60.jpeg",
        "path": "file:C:/Users/Full%20Scale/Documents/MSIT/PythonScipt/clahe-output-img/sea%20grass_60.jpeg",
        "size": {
            "width": 286,
            "height": 200
        },
        "state": 2,
        "type": 1
    },
    "regions": [
        {
            "id": "0WfsdvYMD",
            "type": "RECTANGLE",
            "tags": [
                "seagrass"
            ],
            "boundingBox": {
                "height": 66.54298460328734,
                "width": 47.72848736358524,
                "left": 25.348036631226694,
                "top": 19.1403815388016
            },
            "points": [
                {
                    "x": 25.348036631226694,
                    "y": 19.1403815388016
                },
                {
                    "x": 73.07652399481194,
                    "y": 19.1403815388016
                },
                {
                    "x": 73.07652399481194,
                    "y": 85.68336614208893
                },
                {
                    "x": 25.348036631226694,
                    "y": 85.68336614208893
                }
            ]
        },
        {
            "id": "iLFFjc0by",
            "type": "RECTANGLE",
            "tags": [
                "seagrass"
            ],
            "boundingBox": {
                "height": 68.27458256029684,
                "width": 64.79205251018361,
                "left": 81.23735408560312,
                "top": 21.119358720938656
            },
            "points": [
                {
                    "x": 81.23735408560312,
                    "y": 21.119358720938656
                },
                {
                    "x": 146.02940659578672,
                    "y": 21.119358720938656
                },
                {
                    "x": 146.02940659578672,
                    "y": 89.3939412812355
                },
                {
                    "x": 81.23735408560312,
                    "y": 89.3939412812355
                }
            ]
        },
        {
            "id": "okiQKgVsO",
            "type": "RECTANGLE",
            "tags": [
                "seagrass"
            ],
            "boundingBox": {
                "height": 62.58504156278988,
                "width": 47.233887827040775,
                "left": 160.86727948813433,
                "top": 25.81941678926542
            },
            "points": [
                {
                    "x": 160.86727948813433,
                    "y": 25.81941678926542
                },
                {
                    "x": 208.1011673151751,
                    "y": 25.81941678926542
                },
                {
                    "x": 208.1011673151751,
                    "y": 88.4044583520553
                },
                {
                    "x": 160.86727948813433,
                    "y": 88.4044583520553
                }
            ]
        },
        {
            "id": "-7KbscaH6",
            "type": "RECTANGLE",
            "tags": [
                "seagrass"
            ],
            "boundingBox": {
                "height": 64.31663385791106,
                "width": 35.61089494163424,
                "left": 222.69175741984841,
                "top": 26.066790352504636
            },
            "points": [
                {
                    "x": 222.69175741984841,
                    "y": 26.066790352504636
                },
                {
                    "x": 258.30265236148267,
                    "y": 26.066790352504636
                },
                {
                    "x": 258.30265236148267,
                    "y": 90.3834242104157
                },
                {
                    "x": 222.69175741984841,
                    "y": 90.3834242104157
                }
            ]
        },
        {
            "id": "2_OFAo_W9",
            "type": "RECTANGLE",
            "tags": [
                "seagrass"
            ],
            "boundingBox": {
                "height": 56.400742115027825,
                "width": 42.53522053086495,
                "left": 217.49850190752676,
                "top": 100.03091957219677
            },
            "points": [
                {
                    "x": 217.49850190752676,
                    "y": 100.03091957219677
                },
                {
                    "x": 260.0337224383917,
                    "y": 100.03091957219677
                },
                {
                    "x": 260.0337224383917,
                    "y": 156.4316616872246
                },
                {
                    "x": 217.49850190752676,
                    "y": 156.4316616872246
                }
            ]
        },
        {
            "id": "jioFQMp_p",
            "type": "RECTANGLE",
            "tags": [
                "seagrass"
            ],
            "boundingBox": {
                "height": 39.08472857360273,
                "width": 64.29746429403778,
                "left": 142.81452658884567,
                "top": 109.43104703262696
            },
            "points": [
                {
                    "x": 142.81452658884567,
                    "y": 109.43104703262696
                },
                {
                    "x": 207.11199088288345,
                    "y": 109.43104703262696
                },
                {
                    "x": 207.11199088288345,
                    "y": 148.5157756062297
                },
                {
                    "x": 142.81452658884567,
                    "y": 148.5157756062297
                }
            ]
        },
        {
            "id": "yn_2wuUhh",
            "type": "RECTANGLE",
            "tags": [
                "seagrass"
            ],
            "boundingBox": {
                "height": 40.07421150278293,
                "width": 55.88931745437642,
                "left": 75.79680446520854,
                "top": 112.15213924259334
            },
            "points": [
                {
                    "x": 75.79680446520854,
                    "y": 112.15213924259334
                },
                {
                    "x": 131.68612191958496,
                    "y": 112.15213924259334
                },
                {
                    "x": 131.68612191958496,
                    "y": 152.22635074537627
                },
                {
                    "x": 75.79680446520854,
                    "y": 152.22635074537627
                }
            ]
        },
        {
            "id": "QB37Q2Lot",
            "type": "RECTANGLE",
            "tags": [
                "seagrass"
            ],
            "boundingBox": {
                "height": 65.55350167410714,
                "width": 28.93385214007782,
                "left": 29.304798962386513,
                "top": 92.85714851903118
            },
            "points": [
                {
                    "x": 29.304798962386513,
                    "y": 92.85714851903118
                },
                {
                    "x": 58.23865110246433,
                    "y": 92.85714851903118
                },
                {
                    "x": 58.23865110246433,
                    "y": 158.4106501931383
                },
                {
                    "x": 29.304798962386513,
                    "y": 158.4106501931383
                }
            ]
        },
        {
            "id": "c1gGbxsmU",
            "type": "RECTANGLE",
            "tags": [
                "seagrass"
            ],
            "boundingBox": {
                "height": 26.221405199153523,
                "width": 33.63249679545639,
                "left": 252.36750320454362,
                "top": 161.13173107932803
            },
            "points": [
                {
                    "x": 252.36750320454362,
                    "y": 161.13173107932803
                },
                {
                    "x": 286,
                    "y": 161.13173107932803
                },
                {
                    "x": 286,
                    "y": 187.35313627848154
                },
                {
                    "x": 252.36750320454362,
                    "y": 187.35313627848154
                }
            ]
        },
        {
            "id": "q41UVZeWg",
            "type": "RECTANGLE",
            "tags": [
                "seagrass"
            ],
            "boundingBox": {
                "height": 24.489795918367346,
                "width": 41.54604409857328,
                "left": 192.76870620668168,
                "top": 163.35807616281596
            },
            "points": [
                {
                    "x": 192.76870620668168,
                    "y": 163.35807616281596
                },
                {
                    "x": 234.31475030525496,
                    "y": 163.35807616281596
                },
                {
                    "x": 234.31475030525496,
                    "y": 187.8478720811833
                },
                {
                    "x": 192.76870620668168,
                    "y": 187.8478720811833
                }
            ]
        },
        {
            "id": "kdKV0-ZTm",
            "type": "RECTANGLE",
            "tags": [
                "seagrass"
            ],
            "boundingBox": {
                "height": 22.016071609751855,
                "width": 16.816248397728195,
                "left": 171.5010959412492,
                "top": 168.55288135762117
            },
            "points": [
                {
                    "x": 171.5010959412492,
                    "y": 168.55288135762117
                },
                {
                    "x": 188.3173443389774,
                    "y": 168.55288135762117
                },
                {
                    "x": 188.3173443389774,
                    "y": 190.568952967373
                },
                {
                    "x": 171.5010959412492,
                    "y": 190.568952967373
                }
            ]
        },
        {
            "id": "tq9Hy4Vsd",
            "type": "RECTANGLE",
            "tags": [
                "seagrass"
            ],
            "boundingBox": {
                "height": 19.789726526263912,
                "width": 21.02030483696093,
                "left": 111.40771072724141,
                "top": 165.58442124630392
            },
            "points": [
                {
                    "x": 111.40771072724141,
                    "y": 165.58442124630392
                },
                {
                    "x": 132.42801556420233,
                    "y": 165.58442124630392
                },
                {
                    "x": 132.42801556420233,
                    "y": 185.37414777256782
                },
                {
                    "x": 111.40771072724141,
                    "y": 185.37414777256782
                }
            ]
        },
        {
            "id": "jP2GX_Xsl",
            "type": "RECTANGLE",
            "tags": [
                "seagrass"
            ],
            "boundingBox": {
                "height": 21.52133580705009,
                "width": 12.612191958495462,
                "left": 131.9334273480565,
                "top": 168.0581455549194
            },
            "points": [
                {
                    "x": 131.9334273480565,
                    "y": 168.0581455549194
                },
                {
                    "x": 144.54561930655197,
                    "y": 168.0581455549194
                },
                {
                    "x": 144.54561930655197,
                    "y": 189.5794813619695
                },
                {
                    "x": 131.9334273480565,
                    "y": 189.5794813619695
                }
            ]
        },
        {
            "id": "KcmXUsi71",
            "type": "RECTANGLE",
            "tags": [
                "seagrass"
            ],
            "boundingBox": {
                "height": 22.510830060006956,
                "width": 39.81495138086698,
                "left": 69.61436120019658,
                "top": 167.81076632979185
            },
            "points": [
                {
                    "x": 69.61436120019658,
                    "y": 167.81076632979185
                },
                {
                    "x": 109.42931258106356,
                    "y": 167.81076632979185
                },
                {
                    "x": 109.42931258106356,
                    "y": 190.3215963897988
                },
                {
                    "x": 69.61436120019658,
                    "y": 190.3215963897988
                }
            ]
        },
        {
            "id": "q-KqCrBtH",
            "type": "RECTANGLE",
            "tags": [
                "seagrass"
            ],
            "boundingBox": {
                "height": 21.768715032177642,
                "width": 25.224383916990924,
                "left": 13.230444209275698,
                "top": 159.6475010236694
            },
            "points": [
                {
                    "x": 13.230444209275698,
                    "y": 159.6475010236694
                },
                {
                    "x": 38.45482812626662,
                    "y": 159.6475010236694
                },
                {
                    "x": 38.45482812626662,
                    "y": 181.41621605584703
                },
                {
                    "x": 13.230444209275698,
                    "y": 181.41621605584703
                }
            ]
        },
        {
            "id": "Hv7BUgSco",
            "type": "RECTANGLE",
            "tags": [
                "seagrass"
            ],
            "boundingBox": {
                "height": 23.74768089053803,
                "width": 22.009503910049855,
                "left": 149.24428660272778,
                "top": 168.55288135762117
            },
            "points": [
                {
                    "x": 149.24428660272778,
                    "y": 168.55288135762117
                },
                {
                    "x": 171.25379051277764,
                    "y": 168.55288135762117
                },
                {
                    "x": 171.25379051277764,
                    "y": 192.3005622481592
                },
                {
                    "x": 149.24428660272778,
                    "y": 192.3005622481592
                }
            ]
        }
    ],
    "version": "2.2.0"
}